COPYING
MANIFEST.in
README.md
setup.py
cldoc/__init__.py
cldoc/cmdgenerate.py
cldoc/cmdgir.py
cldoc/cmdinspect.py
cldoc/cmdserve.py
cldoc/cmp.py
cldoc/comment.py
cldoc/defdict.py
cldoc/documentmerger.py
cldoc/example.py
cldoc/fs.py
cldoc/includepaths.py
cldoc/inspecttree.py
cldoc/log.py
cldoc/staticsite.py
cldoc/struct.py
cldoc/tree.py
cldoc/utf8.py
cldoc.egg-info/PKG-INFO
cldoc.egg-info/SOURCES.txt
cldoc.egg-info/dependency_links.txt
cldoc.egg-info/entry_points.txt
cldoc.egg-info/requires.txt
cldoc.egg-info/top_level.txt
cldoc/clang/__init__.py
cldoc/clang/cindex.py
cldoc/clang/enumerations.py
cldoc/data/index.html
cldoc/data/javascript/cldoc.js
cldoc/data/javascript/highlight.js
cldoc/data/javascript/jquery-1.9.1.js
cldoc/data/javascript/jquery-ui-1.10.0.custom.min.js
cldoc/data/javascript/marked.js
cldoc/data/styles/cldoc.css
cldoc/generators/__init__.py
cldoc/generators/generator.py
cldoc/generators/html.py
cldoc/generators/report.py
cldoc/generators/search.py
cldoc/generators/xml.py
cldoc/nodes/__init__.py
cldoc/nodes/category.py
cldoc/nodes/cclass.py
cldoc/nodes/classtemplate.py
cldoc/nodes/constructor.py
cldoc/nodes/conversionfunction.py
cldoc/nodes/cstruct.py
cldoc/nodes/ctype.py
cldoc/nodes/destructor.py
cldoc/nodes/enum.py
cldoc/nodes/enumvalue.py
cldoc/nodes/field.py
cldoc/nodes/function.py
cldoc/nodes/functiontemplate.py
cldoc/nodes/method.py
cldoc/nodes/namespace.py
cldoc/nodes/node.py
cldoc/nodes/root.py
cldoc/nodes/templated.py
cldoc/nodes/templatetypeparameter.py
cldoc/nodes/typedef.py
cldoc/nodes/union.py
cldoc/nodes/variable.py