Metadata-Version: 1.0
Name: cldoc
Version: 1.11.1
Summary: clang based documentation generator for C/C++
Home-page: http://jessevdk.github.com/cldoc
Author: Jesse van den Kieboom
Author-email: jessevdk@gmail.com
License: GPLv2
Keywords: clang,c++,documentation
Platform: UNKNOWN
